pytest_splunk_addon/.ignore_splunk_internal_errors
pytest_splunk_addon/CIM_Models/__init__.py
pytest_splunk_addon/CIM_Models/datamodel_definition.py
pytest_splunk_addon/__init__.py
pytest_splunk_addon/addon_parser/__init__.py
pytest_splunk_addon/addon_parser/eventtype_parser.py
pytest_splunk_addon/addon_parser/fields.py
pytest_splunk_addon/addon_parser/props_parser.py
pytest_splunk_addon/addon_parser/savedsearches_parser.py
pytest_splunk_addon/addon_parser/tags_parser.py
pytest_splunk_addon/addon_parser/transforms_parser.py
pytest_splunk_addon/app_test_generator.py
pytest_splunk_addon/cim_compliance/__init__.py
pytest_splunk_addon/cim_compliance/base_report.py
pytest_splunk_addon/cim_compliance/base_table.py
pytest_splunk_addon/cim_compliance/cim_report_generator.py
pytest_splunk_addon/cim_compliance/markdown_report.py
pytest_splunk_addon/cim_compliance/markdown_table.py
pytest_splunk_addon/cim_compliance/plugin.py
pytest_splunk_addon/cim_tests/CommonFields.json
pytest_splunk_addon/cim_tests/DatamodelSchema.json
pytest_splunk_addon/cim_tests/__init__.py
pytest_splunk_addon/cim_tests/base_schema.py
pytest_splunk_addon/cim_tests/data_model.py
pytest_splunk_addon/cim_tests/data_model_handler.py
pytest_splunk_addon/cim_tests/data_set.py
pytest_splunk_addon/cim_tests/field_test_adapter.py
pytest_splunk_addon/cim_tests/field_test_helper.py
pytest_splunk_addon/cim_tests/json_schema.py
pytest_splunk_addon/cim_tests/test_generator.py
pytest_splunk_addon/cim_tests/test_templates.py
pytest_splunk_addon/data_models/Alerts.json
pytest_splunk_addon/data_models/Authentication.json
pytest_splunk_addon/data_models/Certificates.json
pytest_splunk_addon/data_models/Change.json
pytest_splunk_addon/data_models/Compute_Inventory.json
pytest_splunk_addon/data_models/DLP.json
pytest_splunk_addon/data_models/Data_Access.json
pytest_splunk_addon/data_models/Databases.json
pytest_splunk_addon/data_models/Email.json
pytest_splunk_addon/data_models/Endpoint.json
pytest_splunk_addon-6.1.1.dist-info/LICENSE
pytest_splunk_addon-6.1.1.dist-info/METADATA
pytest_splunk_addon-6.1.1.dist-info/WHEEL
pytest_splunk_addon-6.1.1.dist-info/entry_points.txt
pytest_splunk_addon-6.1.1.dist-info/RECORD
