Metadata-Version: 2.1
Name: pytest-splunk-addon
Version: 6.1.1
Summary: A Dynamic test tool for Splunk Apps and Add-ons
License: Apache-2.0
Author: Splunk
Author-email: addonfactory@splunk.com
Requires-Python: >=3.7,<4.0
Classifier: Framework :: Pytest
Classifier: Intended Audience :: Developers
Classifier: License :: OSI Approved :: Apache Software License
Classifier: Operating System :: OS Independent
Classifier: Programming Language :: Python
Classifier: Programming Language :: Python :: 3
Classifier: Programming Language :: Python :: 3.7
Classifier: Programming Language :: Python :: 3.8
Classifier: Programming Language :: Python :: 3.9
Classifier: Programming Language :: Python :: 3.10
Classifier: Programming Language :: Python :: 3.11
Classifier: Topic :: Software Development :: Testing
Requires-Dist: Faker (>=18.12.0,<19.0.0)
Requires-Dist: addonfactory-splunk-conf-parser-lib
Requires-Dist: certifi (>=2024.7.4,<2025.0.0)
Requires-Dist: defusedxml (>=0.7.1,<0.8.0)
Requires-Dist: filelock (>=3.0,<4.0)
Requires-Dist: jsonschema (>=4.17.3,<5.0.0)
Requires-Dist: junitparser (>=4.0.0,<5.0.0)
Requires-Dist: pytest (>5.4.0,<8)
Requires-Dist: pytest-ordering (>=0.6,<0.7)
Requires-Dist: pytest-xdist (>=3.5.0,<4.0.0)
Requires-Dist: requests (>=2.31.0,<3.0.0)
Requires-Dist: splunk-sdk (>=1.6)
Requires-Dist: splunksplwrapper (>=1.1.1,<2.0.0)
Requires-Dist: urllib3 (<2)
Requires-Dist: xmlschema (>=2.5.1,<3.0.0)
Requires-Dist: xmltodict (>=0.14.0,<0.15.0)
Requires-Dist: zipp (>=3.6.0,<4.0.0)
